{
  "id": "populaerkultur",
  "name": "Populærkultur",
  "icon": "🎬",
  "color": "#ffb703",
  "image": "bilder/merker/populaerkultur.PNG",
  "description": "For dem som forstår samtiden – hvem vi siterer, ser og følger. Popkultur er vår tids folkeeventyr.",
  "tiers": [
    {
      "label": "Publikum",
      "threshold": 5
    },
    {
      "label": "Følger",
      "threshold": 30
    },
    {
      "label": "Fan",
      "threshold": 60
    },
    {
      "label": "Community-medlem",
      "threshold": 80
    },
    {
      "label": "Superfan",
      "threshold": 90
    },
    {
      "label": "Innholdsskaper",
      "threshold": 150
    },
    {
      "label": "Kreatør",
      "threshold": 180
    },
    {
      "label": "Influencer",
      "threshold": 200
    },
    {
      "label": "Profil",
      "threshold": 230
    },
    {
      "label": "Trendsetter",
      "threshold": 260
    },
    {
      "label": "Kultfigur",
      "threshold": 400
    },
    {
      "label": "Ikon",
      "threshold": 700
    },
    {
      "label": "Legende",
      "threshold": 1000
    }
  ],
  "sub": [
    "dataspill",
    "e_sport",
    "fandom",
    "tegneserier",
    "manga_anime",
    "rollespill_og_brettspill",
    "cosplay_og_conventions",
    "memes_og_virale_fenomener"
  ]
}
