[
  {
    "id": "st_lisbon_a_vida_portuguesa_chiado_tradisjonsvarer_og_merkevare",
    "type": "business_history",
    "title": "Tradisjonsvarer som moderne merkevare",
    "year": 2007,
    "place_id": "lisbon_a_vida_portuguesa_chiado",
    "person_id": null,
    "summary": "A Vida Portuguesa i Chiado viser hvordan portugisiske hverdagsprodukter, emballasje, håndverk og nostalgi kan kurateres som moderne handel og merkevareøkonomi.",
    "story": "A Vida Portuguesa / Chiado er et handelsanker for portugisiske tradisjonsprodukter og materialkultur. Butikkonseptet samler varer som såpe, hermetikk, keramikk, papir, tekstiler og små hverdagsobjekter med eldre portugisisk design- og produksjonshistorie.\n\nStedet gjør handel til kulturfortelling. Her er det ikke bare produktet som selges, men historien, emballasjen, grafikken, lukten og følelsen av et nasjonalt hverdagsarkiv. Det gamle og hjemlige blir pakket som moderne kvalitet og identitet.\n\nI History Go bør stedet leses kritisk: nostalgi er også næringsliv. Når hverdagsvarer blir kuratert, øker verdien gjennom design, fortelling og plassering i Chiado. Butikken viser hvordan små produkter kan bære store historier om industri, merkevarer og forbruk.",
    "sources": [
      {
        "title": "History Go place registry: lisbon_a_vida_portuguesa_chiado",
        "url": "data/places/naeringsliv/europe/portugal/lisbon/places_lisbon_naeringsliv.json"
      }
    ],
    "tags": ["naeringsliv", "lisboa", "chiado", "handel", "merkevare", "design", "hverdagsvarer", "nostalgi"],
    "related_people": [],
    "related_places": ["lisbon_chiado", "lisbon_armazens_do_chiado", "lisbon_conserveira_de_lisboa"],
    "score": {"narrative": 5, "historical": 4, "source": 4, "play_value": 5, "originality": 5, "total": 23},
    "arc": {
      "start": "Butikken samler portugisiske hverdagsprodukter og eldre emballasjekultur.",
      "middle": "Nostalgi, design og lokal produksjon gjøres til moderne handelsverdi.",
      "end": "Stedet viser hvordan hverdagsvarer kan bli merkevare, kulturarv og forbruk på én gang."
    },
    "next_scenes": [
      {
        "place_id": "lisbon_conserveira_de_lisboa",
        "reason": "Gå videre til et mer spesifikt matvare- og emballasjeanker i Baixa."
      }
    ]
  }
]
